lhutils/__init__.py
lhutils/utils.py
lhutils-0.0.5.dist-info/LICENSE
lhutils-0.0.5.dist-info/METADATA
lhutils-0.0.5.dist-info/WHEEL
lhutils-0.0.5.dist-info/top_level.txt
lhutils-0.0.5.dist-info/RECORD
