Metadata-Version: 2.1
Name: lhutils
Version: 0.0.5
Summary: 对常用代码进行封装，防止自己重复造轮子。
Author-email: lh <tasbox@163.com>
License: Copyright (c) 2018 The Python Packaging Authority        
Project-URL: Homepage, https://github.com/tasbox/lhutils
Project-URL: Bug Tracker, https://github.com/tasbox/lhutils/issues
Classifier: Programming Language :: Python :: 3
Classifier: License :: OSI Approved :: MIT License
Classifier: Operating System :: OS Independent
Requires-Python: >=3.7
License-File: LICENSE
